clean_architecture/__init__.py
clean_architecture/version.py
clean_architecture/domain/__init__.py
clean_architecture/domain/request_object.py
clean_architecture/domain/response_object.py
clean_architecture/domain/use_case.py
clean_architecture/entity/__init__.py
clean_architecture/entity/entity.py
clean_architecture/exception/__init__.py
clean_architecture/exception/bad_request_exception.py
clean_architecture/exception/conflicted_exception.py
clean_architecture/exception/exception.py
clean_architecture/exception/forbidden_exception.py
clean_architecture/exception/method_not_allowed_exception.py
clean_architecture/exception/not_acceptable_exception.py
clean_architecture/exception/not_found_exception.py
clean_architecture/exception/payment_required_exception.py
clean_architecture/exception/precondition_failed_exception.py
clean_architecture/exception/unauthorized_exception.py
clean_architecture/exception/unprocessable_entity_exception.py
clean_architecture/serializer/__init__.py
clean_architecture/serializer/serializer.py
clean_architecture-0.0.3.dist-info/AUTHORS
clean_architecture-0.0.3.dist-info/LICENSE
clean_architecture-0.0.3.dist-info/METADATA
clean_architecture-0.0.3.dist-info/WHEEL
clean_architecture-0.0.3.dist-info/top_level.txt
clean_architecture-0.0.3.dist-info/RECORD
