Metadata-Version: 2.1
Name: clean-architecture
Version: 0.0.3
Summary: UNKNOWN
Home-page: https://github.com/JayStevency/clean-architecture
Author: jaystevency
Author-email: yjy1129@kookmin.ac.kr
License: UNKNOWN
Download-URL: https://github.com/JayStevency/clean-architecture
Platform: UNKNOWN
Classifier: Programming Language :: Python :: 3
Classifier: Programming Language :: Python :: 3.7
Classifier: License :: OSI Approved :: MIT License
Classifier: Operating System :: OS Independent
